morpheus/render/__init__.py
morpheus/render/main.py
morpheus_mail-1.0.41.dist-info/licenses/LICENSE
morpheus_mail-1.0.41.dist-info/METADATA
morpheus_mail-1.0.41.dist-info/WHEEL
morpheus_mail-1.0.41.dist-info/top_level.txt
morpheus_mail-1.0.41.dist-info/zip-safe
morpheus_mail-1.0.41.dist-info/RECORD
